README.rst
setup.py
sgtools/__init__.py
sgtools/utils.py
sgtools.egg-info/PKG-INFO
sgtools.egg-info/SOURCES.txt
sgtools.egg-info/dependency_links.txt
sgtools.egg-info/entry_points.txt
sgtools.egg-info/requires.txt
sgtools.egg-info/top_level.txt
sgtools/abstractions/__init__.py
sgtools/abstractions/sgengine.py
sgtools/abstractions/sgmanager.py
sgtools/cli/__init__.py
sgtools/cli/sgmanager.py
sgtools/cli/sgtables.py
tests/__init__.py
tests/abstractions/__init__.py
tests/abstractions/test_sgengine.py
tests/cli/__init__.py
tests/cli/sgtables.py