Metadata-Version: 1.1
Name: sgtools
Version: 0.5
Summary: Standard UNIX tools for manipulating AWS security group rules
Home-page: http://github.com/RetailMeNot/sgtools
Author: Matthew Wedgwood
Author-email: mw@rmn.com
License: MIT
Platform: UNKNOWN
Classifier: Development Status :: 2 - Pre-Alpha
Classifier: Intended Audience :: Developers
Classifier: License :: OSI Approved :: MIT License
Classifier: Operating System :: OS Independent
Classifier: Topic :: Internet
Classifier: Programming Language :: Python :: 2
Classifier: Programming Language :: Python :: 2.7
Classifier: Programming Language :: Python :: 3
Classifier: Topic :: Internet
